{
	"teams": [
		{
			"name": "Blizzard Brigade",
			"player": "Bobex",
			"logo": "bobex",
			"pokemon": [""]
		},
		{
			"name": "Dyken Domage",
			"player": "Jonas",
			"logo": "jonas",
			"pokemon": [""]
		},
		{
			"name": "Gliscor Rangers",
			"player": "Danny",
			"logo": "danny",
			"pokemon": [""]
		},
		{
			"name": "ImpoLeos Imperium",
			"player": "Leo",
			"logo": "leo",
			"pokemon": [""]
		},
		{
			"name": "Münsteraner Wolwerocks",
			"player": "Felix",
			"logo": "felix",
			"pokemon": ["latios", "heatran"]
		},
		{
			"name": "PSV Nilsoking",
			"player": "PPV",
			"logo": "ppv",
			"pokemon": ["great-tusk", "primarina"]
		},
		{
			"name": "Twindrake City Thundurus",
			"player": "Philipp",
			"logo": "niklas",
			"pokemon": ["iron-treads"]
		},
		{
			"name": "Wake Me Up",
			"player": "Alex",
			"logo": "alex",
			"pokemon": [""]
		},
		{
			"name": "Atalanta Fletiamo",
			"player": "Nico",
			"logo": "nico",
			"pokemon": [""]
		},
		{
			"name": "Bellektro Ghetto",
			"player": "Max",
			"logo": "max",
			"pokemon": [""]
		},
		{
			"name": "G-Town Glowkings",
			"player": "Till",
			"logo": "till",
			"pokemon": [""]
		},
		{
			"name": "Große Demeteros Apokalypse",
			"player": "Niklas",
			"logo": "niklas",
			"pokemon": [""]
		},
		{
			"name": "Harte Schale Harter Kern",
			"player": "Oli",
			"logo": "oli",
			"pokemon": [""]
		},
		{
			"name": "Inter Flyland",
			"player": "Flo",
			"logo": "flo",
			"pokemon": [""]
		},
		{
			"name": "Laustos Münster",
			"player": "Rick",
			"logo": "rick",
			"pokemon": ["zamazenta", "latias"]
		},
		{
			"name": "Turtinators Titans",
			"player": "Turti",
			"logo": "turti",
			"pokemon": ["iron-bundle", "tyranitar"]
		}
	]
}
